LICENSE
MANIFEST.in
README.md
setup.py
djmailgun/__init__.py
djmailgun/admin.py
djmailgun/errors.py
djmailgun/models.py
djmailgun.egg-info/PKG-INFO
djmailgun.egg-info/SOURCES.txt
djmailgun.egg-info/dependency_links.txt
djmailgun.egg-info/pbr.json
djmailgun.egg-info/requires.txt
djmailgun.egg-info/top_level.txt
djmailgun/backends/__init__.py
djmailgun/backends/v1.py
djmailgun/backends/v2.py
djmailgun/backends/v3.py
djmailgun/migrations/0001_initial.py
djmailgun/migrations/__init__.py