Metadata-Version: 1.1
Name: djmailgun
Version: 0.0.1
Summary: A simple drop-in mail backend for Django
Home-page: http://www.example.com/
Author: Dmitry Yuzhakov
Author-email: dmtry88@gmail.com
License: MIT License
Keywords: django mailgun email
Platform: UNKNOWN
Classifier: Environment :: Web Environment
Classifier: Framework :: Django
Classifier: Intended Audience :: Developers
Classifier: License :: OSI Approved :: BSD License
Classifier: Operating System :: OS Independent
Classifier: Programming Language :: Python
Classifier: Programming Language :: Python :: 3
Classifier: Programming Language :: Python :: 3.4
Classifier: Topic :: Internet :: WWW/HTTP
Classifier: Topic :: Internet :: WWW/HTTP :: Dynamic Content
